[
    {
        "id": "onix-1-0",
        "model": "Chevrolet Onix (0km)",
        "version": "1.0",
        "price": "R$ 87.790",
        "color": "#DC2626",
        "details": {
            "Motor": "1.0 Aspirado de 82 cv",
            "Segurança": "6 Airbags, Controle de Estabilidade (ESC)",
            "Câmbio": "Manual de 6 marchas",
            "Destaques": "Pacote de segurança completo de série"
        },
        "scores": {
            "desempenho": 6,
            "consumo": 10,
            "seguranca": 8,
            "conforto": 6,
            "tecnologia": 4
        },
        "fullDetails": {
            "desempenho": {
                "Motorização": "1.0 Aspirado, 3 cilindros, 12 válvulas",
                "Alimentação": "Aspiração natural com injeção multiponto",
                "Potência máxima (cv)": "82 (Etanol) / 78 (Gasolina) @ 6.400 rpm",
                "Torque (kgf.m)": "10,6 (Etanol) / 9,6 (Gasolina) @ 4.100 rpm",
                "Transmissão": "Manual de 6 marchas",
                "Aceleração (0-100 km/h)": "13,3 s",
                "Velocidade Máxima": "167 km/h"
            },
            "consumo": {
                "Consumo Urbano (km/l)": "9,4 (Etanol) / 13,3 (Gasolina)",
                "Consumo Rodoviário (km/l)": "11,5 (Etanol) / 16,6 (Gasolina)",
                "Eficiência Energética": "1,46 MJ/km",
                "Tanque de Combustível": "44 L"
            },
            "dimensoes": {
                "Comprimento": "4.163 mm",
                "Largura": "1.730 mm",
                "Altura": "1.476 mm",
                "Entre-eixos": "2.551 mm",
                "Porta-malas (VDA)": "303 L",
                "Porta-malas (bancos rebatidos)": "Aprox. 1.113 L",
                "Peso": "1.037 kg"
            },
            "tecnologia": {
                "Sistema de Áudio": "Rádio AM/FM com Bluetooth e 4 alto-falantes",
                "Conectividade": "Porta USB dianteira",
                "Painel de Instrumentos": "Analógico com computador de bordo"
            },
            "conforto": {
                "Direção": "Elétrica Progressiva",
                "Ar-condicionado": "Sim, manual",
                "Ajuste do Volante": "Ajuste de altura",
                "Ajuste do Banco do Motorista": "Ajuste de altura",
                "Vidros e Travas": "Vidros elétricos dianteiros, travas elétricas",
                "Capacidade": "5 passageiros"
            },
            "seguranca": {
                "Airbags": "6 Airbags (2 frontais, 2 laterais, 2 de cortina)",
                "Sistemas Ativos": "Freios ABS com EBD, Controle de Estabilidade (ESC), Controle de Tração (TCS)",
                "Sistemas Passivos": "Estrutura com zonas de deformação programada, ISOFIX",
                "Sistemas Auxiliares": "Assistente de partida em rampa (HSA), Monitoramento de pressão dos pneus (TPMS)",
                "Certificação de Segurança": "5 estrelas (Latin NCAP - protocolo de 2019)"
            }
        }
    },
    {
        "id": "onix-lt-1-0",
        "model": "Chevrolet Onix (0km)",
        "version": "LT 1.0",
        "price": "R$ 95.050",
        "color": "#B91C1C",
        "details": {
            "Motor": "1.0 Aspirado de 82 cv",
            "Segurança": "6 Airbags, Controle de Estabilidade (ESC)",
            "Câmbio": "Manual de 6 marchas",
            "Destaques": "Adiciona MyLink 8\" sem fio, USB traseiro"
        },
        "scores": {
            "desempenho": 6,
            "consumo": 10,
            "seguranca": 8,
            "conforto": 7,
            "tecnologia": 7
        },
        "fullDetails": {
            "desempenho": {
                "Motorização": "1.0 Aspirado, 3 cilindros, 12 válvulas",
                "Alimentação": "Aspiração natural com injeção multiponto",
                "Potência máxima (cv)": "82 (Etanol) / 78 (Gasolina) @ 6.400 rpm",
                "Torque (kgf.m)": "10,6 (Etanol) / 9,6 (Gasolina) @ 4.100 rpm",
                "Transmissão": "Manual de 6 marchas",
                "Aceleração (0-100 km/h)": "13,3 s",
                "Velocidade Máxima": "167 km/h"
            },
            "consumo": {
                "Consumo Urbano (km/l)": "9,4 (Etanol) / 13,3 (Gasolina)",
                "Consumo Rodoviário (km/l)": "11,5 (Etanol) / 16,6 (Gasolina)",
                "Eficiência Energética": "1,46 MJ/km",
                "Tanque de Combustível": "44 L"
            },
            "dimensoes": {
                "Comprimento": "4.163 mm",
                "Largura": "1.730 mm",
                "Altura": "1.476 mm",
                "Entre-eixos": "2.551 mm",
                "Porta-malas (VDA)": "303 L",
                "Peso": "1.037 kg"
            },
            "tecnologia": {
                "Central Multimídia": "MyLink de 8\" com espelhamento sem fio (Apple CarPlay/Android Auto)",
                "Conectividade": "2 Portas USB para o banco traseiro",
                "Painel de Instrumentos": "Analógico com computador de bordo"
            },
            "conforto": {
                "Direção": "Elétrica Progressiva",
                "Ar-condicionado": "Sim, manual",
                "Ajuste do Volante": "Ajuste de altura",
                "Ajuste do Banco do Motorista": "Ajuste de altura",
                "Retrovisores": "Elétricos",
                "Diferenciais": "Volante multifuncional"
            },
            "seguranca": {
                "Airbags": "6 Airbags (2 frontais, 2 laterais, 2 de cortina)",
                "Sistemas Ativos": "Freios ABS com EBD, Controle de Estabilidade (ESC), Controle de Tração (TCS)",
                "Sistemas Passivos": "Estrutura com zonas de deformação programada, ISOFIX",
                "Sistemas Auxiliares": "Assistente de partida em rampa (HSA), Monitoramento de pressão dos pneus (TPMS)",
                "Certificação de Segurança": "5 estrelas (Latin NCAP - protocolo de 2019)"
            }
        }
    },
    {
        "id": "onix-100-anos-turbo-at",
        "model": "Chevrolet Onix (0km)",
        "version": "100 Anos Turbo AT",
        "price": "R$ 125.590",
        "color": "#991B1B",
        "details": {
            "Motor": "1.0 Turbo de 116 cv",
            "Segurança": "Alerta de ponto cego, 6 Airbags",
            "Conforto": "Ar digital, Easy Park, Carregador sem fio",
            "Destaques": "Edição especial com visual e itens exclusivos"
        },
        "scores": {
            "desempenho": 8,
            "consumo": 8,
            "seguranca": 9,
            "conforto": 9,
            "tecnologia": 9
        },
        "fullDetails": {
            "desempenho": {
                "Motorização": "1.0 Turbo, 3 cilindros, 12 válvulas",
                "Alimentação": "Turbocompressor com injeção multiponto",
                "Potência máxima (cv)": "116 (Etanol/Gasolina) @ 5.500 rpm",
                "Torque (kgf.m)": "16,8 (Etanol) / 16,3 (Gasolina) @ 2.000 rpm",
                "Transmissão": "Automática de 6 marchas",
                "Aceleração (0-100 km/h)": "10,1 s",
                "Velocidade Máxima": "187 km/h"
            },
            "consumo": {
                "Consumo Urbano (km/l)": "8,6 (Etanol) / 12,3 (Gasolina)",
                "Consumo Rodoviário (km/l)": "10,8 (Etanol) / 15,1 (Gasolina)",
                "Eficiência Energética": "1,63 MJ/km",
                "Tanque de Combustível": "44 L"
            },
            "dimensoes": {
                "Comprimento": "4.163 mm",
                "Largura": "1.730 mm",
                "Altura": "1.476 mm",
                "Entre-eixos": "2.551 mm",
                "Porta-malas (VDA)": "303 L",
                "Peso": "1.113 kg"
            },
            "tecnologia": {
                "Central Multimídia": "MyLink de 8\" com espelhamento sem fio",
                "Conectividade": "OnStar, Wi-Fi nativo, Projeção sem fio",
                "Sistemas de Assistência": "Assistente de estacionamento automático (Easy Park)",
                "Painel de Instrumentos": "Analógico com computador de bordo avançado",
                "Diferenciais": "Carregador de celular por indução (Wireless Charger)"
            },
            "conforto": {
                "Direção": "Elétrica Progressiva",
                "Ar-condicionado": "Automático digital",
                "Ajuste do Volante": "Ajuste de altura e profundidade",
                "Chave": "Chave presencial com partida por botão",
                "Materiais do Acabamento": "Bancos e volante com revestimento premium em dois tons (preto e vermelho)",
                "Diferenciais": "Logos '100 Anos', emblemas escurecidos, rodas de liga leve 16\" exclusivas"
            },
            "seguranca": {
                "Airbags": "6 Airbags (2 frontais, 2 laterais, 2 de cortina)",
                "Sistemas Ativos": "Freios ABS com EBD, Controle de Estabilidade (ESC), Controle de Tração (TCS)",
                "Sistemas de Assistência (ADAS)": "Alerta de Ponto Cego",
                "Sistemas Auxiliares": "HSA, TPMS, Sensores de estacionamento dianteiro, lateral e traseiro",
                "Certificação de Segurança": "5 estrelas (Latin NCAP - protocolo de 2019)"
            }
        }
    }
]